{
  "audiovisual_files": {
    "8107657e-8aa1-4e25-9680-2fecd6510260": {
      "label": "Episode 166: NATO Alliance",
      "is_offline": false,
      "file_type": "Audio",
      "file_url": "https://dn711205.ca.archive.org/0/items/episode-73_202606/Episode%20166.mp3",
      "duration": 2975
    }
  },
  "auto_generate_web_page": true,
  "label": "Episode 166: NATO Alliance",
  "created_at": "2026-06-08T20:59:14.531Z",
  "created_by": "raymondhyser",
  "updated_at": "2026-06-25T20:56:05.363Z",
  "updated_by": "raymondhyser",
  "av_file_order": [
    "8107657e-8aa1-4e25-9680-2fecd6510260"
  ],
  "description": [
    {
      "type": "paragraph",
      "children": [
        {
          "text": "In this episode, Jeremi and Zachary talk with special guests, Dr. James Goldgeier and Dr. Joshua Shifrinson, about NATO (North Atlantic Treaty Organization), and discuss why the alliance exists, the roll it has played, and how we should think about the alliance’s future."
        }
      ]
    },
    {
      "type": "paragraph",
      "children": [
        {
          "text": ""
        }
      ]
    },
    {
      "type": "paragraph",
      "children": [
        {
          "text": "Zachary sets the scene with his poem, “Transatlantic Elegy”."
        }
      ]
    },
    {
      "type": "paragraph",
      "children": [
        {
          "text": "\nJames Goldgeier is a Professor of International Relations and served as Dean of the School of International Service at American University from 2011-17. He is also a Robert Bosch Senior Visiting Fellow at the Center on the United States and Europe at the Brookings Institution, and he serves as the chair of the State Department Historical Advisory Committee. He has authored or co-authored four books including: "
        },
        {
          "text": "America Between the Wars: From 11/9 to 9/11",
          "italic": true
        },
        {
          "text": " (co-authored with Derek Chollet); "
        },
        {
          "text": "Power and Purpose: U.S. Policy toward Russia after the Cold War ",
          "italic": true
        },
        {
          "text": "(co-authored with Michael McFaul); and"
        },
        {
          "text": " Not Whether But When: The U.S. Decision to Enlarge NATO",
          "italic": true
        },
        {
          "text": ". \n"
        }
      ]
    },
    {
      "type": "paragraph",
      "children": [
        {
          "text": "Joshua Shifrinson is an Associate Professor of International Relations in the Frederick S. Pardee School of Global Studies at Boston University. Shifrinson’s book, "
        },
        {
          "text": "Rising Titans, Falling Giants: How Great Powers Exploit Power Shifts",
          "italic": true
        },
        {
          "text": ", explains why some rising states challenge and prey upon declining great powers, while others seek to support and cooperate with declining states. He has additional related projects on U.S. grand strategy, the durability of NATO, U.S. relations with its allies during and after the Cold War, and the rise of China. His work has appeared in "
        },
        {
          "text": "International Security, the Journal of Strategic Studies, Foreign Affairs",
          "italic": true
        },
        {
          "text": ", and other venues. "
        }
      ]
    },
    {
      "type": "paragraph",
      "children": [
        {
          "text": ""
        }
      ]
    },
    {
      "type": "paragraph",
      "children": [
        {
          "text": "This episode of "
        },
        {
          "italic": true,
          "text": "This is Democracy "
        },
        {
          "text": "was mixed and mastered by Ean Herrera."
        }
      ]
    },
    {
      "type": "paragraph",
      "children": [
        {
          "italic": true,
          "text": ""
        }
      ]
    },
    {
      "type": "paragraph",
      "children": [
        {
          "text": "https://podcasts.la.utexas.edu/this-is-democracy/podcast/this-is-democracy-episode-166-nato-alliance/"
        }
      ]
    }
  ]
}